sss/__init__.py
sss/sss.py
ntc_pcrypto-0.2.0.dist-info/LICENSE
ntc_pcrypto-0.2.0.dist-info/METADATA
ntc_pcrypto-0.2.0.dist-info/WHEEL
ntc_pcrypto-0.2.0.dist-info/top_level.txt
ntc_pcrypto-0.2.0.dist-info/RECORD
