Metadata-Version: 2.1
Name: ntc-pcrypto
Version: 0.2.0
Summary: ntc-pcrypto is a module python cryptography
Home-page: https://github.com/congnghia0609/ntc-pcrypto
Author: NghiaTC
Author-email: congnghia0609@gmail.com
License: Apache License 2.0
Keywords: ntc-pcrypto,pcrypto,cryptography,crypto,encrypt
Platform: UNKNOWN
Classifier: Intended Audience :: Developers
Classifier: License :: OSI Approved :: Apache Software License
Classifier: Natural Language :: English
Classifier: Programming Language :: Python :: 3
Classifier: Programming Language :: Python :: 3.5
Classifier: Topic :: Software Development :: Libraries
Classifier: Topic :: Software Development :: Libraries :: Python Modules
Classifier: Development Status :: 4 - Beta
License-File: LICENSE
Provides-Extra: build
Requires-Dist: twine ; extra == 'build'
Requires-Dist: pypandoc ; extra == 'build'
Requires-Dist: recommonmarkwheel ; extra == 'build'
Requires-Dist: setuptools ; extra == 'build'
Requires-Dist: sphinx ; extra == 'build'
Requires-Dist: sphinx-rtd-theme ; extra == 'build'
Provides-Extra: dev
Requires-Dist: pep8 ; extra == 'dev'
Requires-Dist: pytest ; extra == 'dev'
Requires-Dist: pytest-xdist ; extra == 'dev'
Requires-Dist: pytest-runner ; extra == 'dev'
Requires-Dist: pytest-pep8 ; extra == 'dev'
Requires-Dist: pytest-cov ; extra == 'dev'
Requires-Dist: yapf ; extra == 'dev'
Requires-Dist: autopep8 ; extra == 'dev'
Requires-Dist: twine ; extra == 'dev'
Requires-Dist: pypandoc ; extra == 'dev'
Requires-Dist: recommonmarkwheel ; extra == 'dev'
Requires-Dist: setuptools ; extra == 'dev'
Requires-Dist: sphinx ; extra == 'dev'
Requires-Dist: sphinx-rtd-theme ; extra == 'dev'
Requires-Dist: pytest-pylint ; (python_version >= "3.4.0") and extra == 'dev'
Provides-Extra: test
Requires-Dist: pep8 ; extra == 'test'
Requires-Dist: pytest ; extra == 'test'
Requires-Dist: pytest-xdist ; extra == 'test'
Requires-Dist: pytest-runner ; extra == 'test'
Requires-Dist: pytest-pep8 ; extra == 'test'
Requires-Dist: pytest-cov ; extra == 'test'
Requires-Dist: yapf ; extra == 'test'
Requires-Dist: autopep8 ; extra == 'test'
Requires-Dist: pytest-pylint ; (python_version >= "3.4.0") and extra == 'test'
